excalidraw_mcp/__init__.py
excalidraw_mcp/__main__.py
excalidraw_mcp/cli.py
excalidraw_mcp/config.py
excalidraw_mcp/element_factory.py
excalidraw_mcp/http_client.py
excalidraw_mcp/mcp_tools.py
excalidraw_mcp/process_manager.py
excalidraw_mcp/retry_utils.py
excalidraw_mcp/server.py
excalidraw_mcp/.skylos/cache.sqlite
excalidraw_mcp/monitoring/__init__.py
excalidraw_mcp/monitoring/alerts.py
excalidraw_mcp/monitoring/circuit_breaker.py
excalidraw_mcp/monitoring/health_checker.py
excalidraw_mcp/monitoring/metrics.py
excalidraw_mcp/monitoring/supervisor.py
excalidraw_mcp-0.35.3.dist-info/METADATA
excalidraw_mcp-0.35.3.dist-info/WHEEL
excalidraw_mcp-0.35.3.dist-info/entry_points.txt
excalidraw_mcp-0.35.3.dist-info/licenses/LICENSE
excalidraw_mcp-0.35.3.dist-info/RECORD
