Metadata-Version: 2.4
Name: excalidraw-mcp
Version: 0.35.3
Summary: Unofficial MCP server for Excalidraw diagram management with canvas sync
Project-URL: Homepage, https://github.com/lesleslie/excalidraw-mcp
Project-URL: Repository, https://github.com/lesleslie/excalidraw-mcp
Author-email: Les Leslie <les@wedgwoodwebworks.com>
License: BSD-3-CLAUSE
License-File: LICENSE
Classifier: Development Status :: 4 - Beta
Classifier: Intended Audience :: Developers
Classifier: License :: OSI Approved :: BSD License
Classifier: Operating System :: OS Independent
Classifier: Programming Language :: Python :: 3
Classifier: Programming Language :: Python :: 3.13
Classifier: Topic :: Software Development :: Libraries :: Python Modules
Classifier: Topic :: System :: Monitoring
Requires-Python: >=3.13
Requires-Dist: cryptography>=45.0.6
Requires-Dist: fastmcp>=2.11.3
Requires-Dist: httpx[http2]>=0.28.1
Requires-Dist: mcp-common>=0.4.7
Requires-Dist: oneiric>=0.3.6
Requires-Dist: psutil>=6.1.1
Requires-Dist: pydantic>=2.11.7
Requires-Dist: pyjwt>=2.10.1
Requires-Dist: rich>=13.9.4
Requires-Dist: typer>=0.15.1
